<?xml version='1.0' encoding='ISO-8859-1' standalone='no'?>
<root>
<name>Magic Wand</name>
<version>1.0.0.0</version>
<description>Magic Wand tool (2D)
Maintain left mouse button down while moving mouse cursor right/left to increase/decrease tolerance.

By default magic Wand apply to the current active channel tab from the Colormap panel but you can enable Color mode (3 channels image only) by maintaining shift key pressed.

Go to Icy preferences to access some advanced settings.
</description>
<classname>plugins.kernel.roi.tool.plugin.ROIMagicWandPlugin</classname>
</root>
